fioctl/__init__.py
fioctl/accounts.py
fioctl/assets.py
fioctl/audit_logs.py
fioctl/comments.py
fioctl/config.py
fioctl/fio.py
fioctl/fioctl.py
fioctl/presentations.py
fioctl/projects.py
fioctl/review_links.py
fioctl/teams.py
fioctl/upload.py
fioctl/uploader.py
fioctl/users.py
fioctl/utils.py
fioctl-1.1.dist-info/LICENSE
fioctl-1.1.dist-info/METADATA
fioctl-1.1.dist-info/WHEEL
fioctl-1.1.dist-info/entry_points.txt
fioctl-1.1.dist-info/top_level.txt
fioctl-1.1.dist-info/RECORD
