Metadata-Version: 2.1
Name: fioctl
Version: 1.1
Summary: Frame.io cli
Home-page: UNKNOWN
Author: Frame.io, Inc.
Author-email: platform@frame.io
License: MIT
Platform: UNKNOWN
Requires-Dist: Click (==6.7)
Requires-Dist: pyyaml
Requires-Dist: requests
Requires-Dist: tqdm
Requires-Dist: frameioclient (==0.5.1)
Requires-Dist: tabulate
Requires-Dist: token-bucket
Requires-Dist: treelib
Requires-Dist: cached-property
Requires-Dist: furl
